AUTHORS.md
LICENSE
MANIFEST.in
README.rst
setup.py
django_pgcryptoauth.egg-info/PKG-INFO
django_pgcryptoauth.egg-info/SOURCES.txt
django_pgcryptoauth.egg-info/dependency_links.txt
django_pgcryptoauth.egg-info/not-zip-safe
django_pgcryptoauth.egg-info/top_level.txt
pgcryptoauth/__init__.py
pgcryptoauth/hashers.py
pgcryptoauth/models.py
pgcryptoauth/settings.py
tests/__init__.py
tests/settings.py
tests/tests.py